warg_shell/__init__.py
warg_shell/__main__.py
warg_shell/_cli.py
warg_shell/_jon.py
warg_shell/_warg.py
warg_shell-1.1.1.dist-info/METADATA
warg_shell-1.1.1.dist-info/WHEEL
warg_shell-1.1.1.dist-info/entry_points.txt
warg_shell-1.1.1.dist-info/RECORD
