Metadata-Version: 2.3
Name: warg-shell
Version: 1.1.1
Summary: DigitalOcean Warg - SSH-like connection to DigitalOcean PaaS console
License: WTFPL
Author: Rémy Sanchez
Author-email: remy.sanchez@hyperthese.net
Requires-Python: >=3.10,<4.0
Classifier: License :: Other/Proprietary License
Classifier: Programming Language :: Python :: 3
Classifier: Programming Language :: Python :: 3.10
Classifier: Programming Language :: Python :: 3.11
Classifier: Programming Language :: Python :: 3.12
Classifier: Programming Language :: Python :: 3.13
Requires-Dist: click
Requires-Dist: httpx
Requires-Dist: keyring
Requires-Dist: psutil
Requires-Dist: rich
Requires-Dist: rich-click
Requires-Dist: websockets
